odoo/addons/delivery_price_collection_cost/README.rst
odoo/addons/delivery_price_collection_cost/__init__.py
odoo/addons/delivery_price_collection_cost/__manifest__.py
odoo/addons/delivery_price_collection_cost/i18n/delivery_price_collection_cost.pot
odoo/addons/delivery_price_collection_cost/i18n/it.po
odoo/addons/delivery_price_collection_cost/models/__init__.py
odoo/addons/delivery_price_collection_cost/models/delivery_carrier.py
odoo/addons/delivery_price_collection_cost/models/delivery_price_rule.py
odoo/addons/delivery_price_collection_cost/models/sale_order.py
odoo/addons/delivery_price_collection_cost/models/sale_order_line.py
odoo/addons/delivery_price_collection_cost/readme/CONTRIBUTORS.rst
odoo/addons/delivery_price_collection_cost/readme/DESCRIPTION.rst
odoo/addons/delivery_price_collection_cost/readme/USAGE.rst
odoo/addons/delivery_price_collection_cost/static/description/icon.png
odoo/addons/delivery_price_collection_cost/static/description/index.html
odoo/addons/delivery_price_collection_cost/tests/__init__.py
odoo/addons/delivery_price_collection_cost/tests/test_delivery_price_collection_cost.py
odoo/addons/delivery_price_collection_cost/views/delivery_carrier_views.xml
odoo/addons/delivery_price_collection_cost/views/delivery_price_rule.xml
odoo/addons/delivery_price_collection_cost/wizards/__init__.py
odoo/addons/delivery_price_collection_cost/wizards/choose_delivery_carrier.py
odoo/addons/delivery_price_collection_cost/wizards/choose_delivery_carrier_views.xml
odoo14_addon_delivery_price_collection_cost-14.0.1.0.1.dev4.dist-info/METADATA
odoo14_addon_delivery_price_collection_cost-14.0.1.0.1.dev4.dist-info/WHEEL
odoo14_addon_delivery_price_collection_cost-14.0.1.0.1.dev4.dist-info/top_level.txt
odoo14_addon_delivery_price_collection_cost-14.0.1.0.1.dev4.dist-info/RECORD
